LICENSE
MANIFEST.in
README.rst
setup.py
il2fb/parsers/events/__init__.py
il2fb/parsers/events/actors.py
il2fb/parsers/events/constants.py
il2fb/parsers/events/events.py
il2fb/parsers/events/exceptions.py
il2fb/parsers/events/l10n.py
il2fb/parsers/events/parsers.py
il2fb/parsers/events/priority.py
il2fb/parsers/events/rx.py
il2fb/parsers/events/tx.py
il2fb/parsers/events/locale/en/LC_MESSAGES/il2fb-events-parser.mo
il2fb/parsers/events/locale/en/LC_MESSAGES/il2fb-events-parser.po
il2fb/parsers/events/locale/ru/LC_MESSAGES/il2fb-events-parser.mo
il2fb/parsers/events/locale/ru/LC_MESSAGES/il2fb-events-parser.po
il2fb_events_parser.egg-info/PKG-INFO
il2fb_events_parser.egg-info/SOURCES.txt
il2fb_events_parser.egg-info/dependency_links.txt
il2fb_events_parser.egg-info/namespace_packages.txt
il2fb_events_parser.egg-info/requires.txt
il2fb_events_parser.egg-info/top_level.txt
requirements/dist.txt